{
  "id": "brender-critical-edition-packet",
  "target_id": "brender",
  "task_type": "build-archive-packet",
  "status": "portable-render-lane-published",
  "public_notes": "The BRender critical-edition portable pure-C render lane is published as the standalone brender-archival repository. From the pinned public v1.3.2 snapshot at d88d0ed41122664b9781015b517db64353e16f19, the engine-revival materializer builds the FLOAT core library and twelve verifying CTest rungs: vector math, framework startup, wireframe, v1db scene graph, flat fill, depth buffering, perspective-correct texturing, native datafile model loading, UV material rendering, multi-part loading, Gouraud shading, and hidden-line SVG plotter output. CTest 12/12 passed and readiness score 86 is recorded. Deferred work remains explicit: x64 pointer-width portability, period softrend translation, native .mat/.pal/.pix resolution, semantic compatibility-stub coverage, FIXED variants, drivers, packaged release binaries, and a full viewer.",
  "inputs": ["public source branches", "community preservation index", "BRender accessions", "generated portable-core harness and render-smoke ladder", "brender-production-readiness record"],
  "outputs": ["standalone archival packet", "version graph", "reproducible build checklist", "portable pure-C render harness generator", "twelve verifying render smokes (vector math through hidden-line plotter)", "public-safe render captures"],
  "blocked_by": [],
  "evidence_checkpoint": {
    "id": "brender-v132-portable-core-plotter-2026-07-03",
    "stage": "portable-core-plotter-lane-passing",
    "passed": 12,
    "total": 12,
    "source_snapshot": "d88d0ed41122664b9781015b517db64353e16f19"
  },
  "source_ids": ["foone-brender-v132", "foone-brender-3dmm", "blazingrender-index"]
}
